bomisspell/__init__.py
bomisspell/exceptions.py
bomisspell/mingzhi.py
bomisspell/option_generator.py
bomisspell/sgnon_jung.py
bomisspell/utils.py
bomisspell/yang_jug.py
bomisspell/resources/load_mapping.py
bomisspell/resources/mapping.txt
bomisspell/resources/mingzhi_mapping.yaml
bomisspell-0.0.11.dist-info/METADATA
bomisspell-0.0.11.dist-info/WHEEL
bomisspell-0.0.11.dist-info/top_level.txt
bomisspell-0.0.11.dist-info/RECORD
