Metadata-Version: 2.1
Name: bomisspell
Version: 0.0.11
Summary: Generates misspelled tibetan word of a given word
Home-page: https://github.com/potala-dev/bomisspell
Author: Tenzin Kaldan
Author-email: kaldantenzin@gmail.com
License: Apache2
Platform: UNKNOWN
Classifier: Programming Language :: Python :: 3
Classifier: License :: OSI Approved :: MIT License
Classifier: Operating System :: OS Independent
Requires-Python: >=3.6
Requires-Dist: botok (<8.0,>=0.8.6)
Requires-Dist: pylibyaml (<2.0,>=0.1.0)
